uvengine/__init__.py
uvengine/configuration.py
uvengine/mapping_model.py
uvengine/uvengine.py
uvengine/variation_point.py
uvengine-1.0.1.dist-info/METADATA
uvengine-1.0.1.dist-info/WHEEL
uvengine-1.0.1.dist-info/top_level.txt
uvengine-1.0.1.dist-info/RECORD
