Metadata-Version: 2.4
Name: uvengine
Version: 1.0.1
Summary: Variability resolution engine for UVL models and text-based implementation artifacts.
Author-email: José Miguel Horcas <horcas@uma.es>
License-Expression: GPL-3.0-or-later
Project-URL: Homepage, https://uvengine.github.io/
Project-URL: GitHub, https://github.com/UVengine/uvengine
Classifier: Programming Language :: Python :: 3
Classifier: Operating System :: OS Independent
Requires-Python: >=3.10
Requires-Dist: flamapy~=2.1.0.dev0
Requires-Dist: flamapy-fm~=2.1.0.dev0
Requires-Dist: Jinja2~=3.1.3
